temporals/__init__.py
temporals/duration.py
temporals/exceptions.py
temporals/utils.py
temporals/interfaces/__init__.py
temporals/interfaces/base_period.py
temporals/interfaces/date_period.py
temporals/interfaces/datetime_period.py
temporals/interfaces/period_duration.py
temporals/interfaces/time_period.py
temporals/pydatetime/__init__.py
temporals/pydatetime/interface.py
temporals/pydatetime/periods.py
temporals/pydatetime/utils.py
temporals/pydatetime/tests/__init__.py
temporals/pydatetime/tests/test_absoluteperiod.py
temporals/pydatetime/tests/test_dateperiod.py
temporals/pydatetime/tests/test_duration.py
temporals/pydatetime/tests/test_timeperiod.py
temporals/pydatetime/tests/test_wallclockperiod.py
temporals-3.2.0.dist-info/licenses/LICENSE
temporals-3.2.0.dist-info/METADATA
temporals-3.2.0.dist-info/WHEEL
temporals-3.2.0.dist-info/top_level.txt
temporals-3.2.0.dist-info/RECORD
